legion/__init__.py
legion/agents/__init__.py
legion/agents/base.py
legion/agents/decorators.py
legion/blocks/__init__.py
legion/blocks/base.py
legion/blocks/decorators.py
legion/errors/__init__.py
legion/errors/exceptions.py
legion/exceptions.py
legion/graph/__init__.py
legion/graph/builder.py
legion/graph/channel_manager.py
legion/graph/channels.py
legion/graph/checkpointing.py
legion/graph/component_coordinator.py
legion/graph/coordinator.py
legion/graph/decorators.py
legion/graph/edges/__init__.py
legion/graph/edges/base.py
legion/graph/edges/conditional.py
legion/graph/edges/registry.py
legion/graph/edges/routing.py
legion/graph/edges/validator.py
legion/graph/graph.py
legion/graph/nodes/__init__.py
legion/graph/nodes/agent.py
legion/graph/nodes/base.py
legion/graph/nodes/block.py
legion/graph/nodes/chain.py
legion/graph/nodes/decorators.py
legion/graph/nodes/execution.py
legion/graph/nodes/graph.py
legion/graph/nodes/registry.py
legion/graph/nodes/team.py
legion/graph/retry.py
legion/graph/state.py
legion/graph/update_protocol.py
legion/groups/__init__.py
legion/groups/base.py
legion/groups/chain.py
legion/groups/decorators.py
legion/groups/team.py
legion/groups/team_tools.py
legion/groups/types.py
legion/interface/__init__.py
legion/interface/base.py
legion/interface/decorators.py
legion/interface/schemas.py
legion/interface/tools.py
legion/memory/base.py
legion/memory/providers/memory.py
legion/monitoring/__init__.py
legion/monitoring/analysis.py
legion/monitoring/collectors.py
legion/monitoring/decorators.py
legion/monitoring/events/__init__.py
legion/monitoring/events/agent.py
legion/monitoring/events/base.py
legion/monitoring/events/chain.py
legion/monitoring/events/team.py
legion/monitoring/metrics.py
legion/monitoring/monitors.py
legion/monitoring/registry.py
legion/monitoring/storage/__init__.py
legion/monitoring/storage/base.py
legion/monitoring/storage/config.py
legion/monitoring/storage/factory.py
legion/monitoring/storage/memory.py
legion_ai-0.1.5.dist-info/LICENSE
legion_ai-0.1.5.dist-info/METADATA
legion_ai-0.1.5.dist-info/WHEEL
legion_ai-0.1.5.dist-info/RECORD
