Metadata-Version: 2.3
Name: legion-ai
Version: 0.1.5
Summary: Legion is a flexible and provider-agnostic framework designed to simplify the creation of sophisticated multi-agent systems
License: MIT
Keywords: ai,agents,multi-agent,llm
Author: Zain Imdad, Hayden Smith
Author-email: zain@llmp.io, hayden@llmp.io
Requires-Python: >=3.11,<4.0
Classifier: Development Status :: 4 - Beta
Classifier: Intended Audience :: Developers
Classifier: License :: OSI Approved :: MIT License
Classifier: Operating System :: OS Independent
Classifier: Programming Language :: Python :: 3
Classifier: Programming Language :: Python :: 3.11
Classifier: Programming Language :: Python :: 3.12
Classifier: Programming Language :: Python :: 3.13
Classifier: Topic :: Scientific/Engineering :: Artificial Intelligence
Classifier: Topic :: Software Development :: Libraries :: Python Modules
Requires-Dist: annotated-types (==0.6.0)
Requires-Dist: anthropic (==0.30.1)
Requires-Dist: asyncio (==3.4.3)
Requires-Dist: bandit (==1.7.8)
Requires-Dist: colorama (==0.4.6)
Requires-Dist: flake8 (==7.0.0)
Requires-Dist: flake8-docstrings (==1.7.0)
Requires-Dist: flake8-import-order (==0.18.2)
Requires-Dist: flake8-quotes (==3.4.0)
Requires-Dist: google-genai (==0.3.0)
Requires-Dist: google-generativeai (==0.8.2)
Requires-Dist: groq (==0.4.2)
Requires-Dist: huggingface-hub (==0.26.3)
Requires-Dist: mypy (==1.9.0)
Requires-Dist: ollama (==0.4.2)
Requires-Dist: openai (==1.55.0)
Requires-Dist: psutil (==5.9.8)
Requires-Dist: pydantic (==2.10.2)
Requires-Dist: python-dotenv (==1.0.1)
Requires-Dist: ruff (==0.3.0)
Requires-Dist: safety (==2.3.5)
Requires-Dist: toml (>=0.10.2,<0.11.0)
Requires-Dist: types-setuptools (==69.2.0.20240317)
Project-URL: Homepage, https://github.com/LLMP-io/Legion
Project-URL: Repository, https://github.com/LLMP-io/Legion
